authoritah/__init__.py
authoritah/authorizer.py
tests/__init__.py
tests/test_authorizer.py
authoritah-0.2.0.dist-info/LICENSE
authoritah-0.2.0.dist-info/METADATA
authoritah-0.2.0.dist-info/WHEEL
authoritah-0.2.0.dist-info/top_level.txt
authoritah-0.2.0.dist-info/RECORD
