Metadata-Version: 2.1
Name: authoritah
Version: 0.2.0
Summary: Lightweight, framework agnostic, context based RBAC authorization library
Home-page: https://github.com/shoppimon/authoritah
Author: Shahar Evron
Author-email: shahar@shoppimon.com
License: Apache 2.0
Platform: UNKNOWN
Classifier: Programming Language :: Python :: 3
Classifier: License :: OSI Approved :: Apache Software License
Classifier: Operating System :: OS Independent
Classifier: Intended Audience :: Developers
Requires-Python: >=3.5.0
Requires-Dist: six
